great_tables/__init__.py
great_tables/_body.py
great_tables/_boxhead.py
great_tables/_databackend.py
great_tables/_export.py
great_tables/_footnotes.py
great_tables/_formats.py
great_tables/_formats_vals.py
great_tables/_gt_data.py
great_tables/_heading.py
great_tables/_helpers.py
great_tables/_locale.py
great_tables/_locations.py
great_tables/_modify_rows.py
great_tables/_options.py
great_tables/_pipe.py
great_tables/_render.py
great_tables/_render_checks.py
great_tables/_row_groups.py
great_tables/_scss.py
great_tables/_source_notes.py
great_tables/_spanners.py
great_tables/_stub.py
great_tables/_stubhead.py
great_tables/_styles.py
great_tables/_substitution.py
great_tables/_tab_create_modify.py
great_tables/_tbl_data.py
great_tables/_text.py
great_tables/_types.py
great_tables/_utils.py
great_tables/_utils_nanoplots.py
great_tables/_utils_render_html.py
great_tables/_utils_render_latex.py
great_tables/_utils_selenium.py
great_tables/gt.py
great_tables/loc.py
great_tables/py.typed
great_tables/quarto.py
great_tables/shiny.py
great_tables/style.py
great_tables/utils_render_common.py
great_tables/vals.py
great_tables/_data_color/__init__.py
great_tables/_data_color/base.py
great_tables/_data_color/constants.py
great_tables/_data_color/palettes.py
great_tables/css/gt_colors.scss
great_tables/css/gt_styles_default.scss
great_tables/data/01-countrypops.csv
great_tables/data/02-sza.csv
great_tables/data/03-gtcars.csv
great_tables/data/04-sp500.csv
great_tables/data/05-pizzaplace.csv
great_tables/data/06-exibble.csv
great_tables/data/07-towny.csv
great_tables/data/08-peeps.csv
great_tables/data/09-films.csv
great_tables/data/10-metro.csv
great_tables/data/11-gibraltar.csv
great_tables/data/12-constants.csv
great_tables/data/13-illness.csv
great_tables/data/14-reactions.csv
great_tables/data/15-photolysis.csv
great_tables/data/16-nuclides.csv
great_tables/data/__init__.py
great_tables/data/x-airquality.csv
great_tables/data/x-islands.csv
great_tables-0.19.0.dist-info/licenses/LICENSE
great_tables-0.19.0.dist-info/METADATA
great_tables-0.19.0.dist-info/WHEEL
great_tables-0.19.0.dist-info/top_level.txt
great_tables-0.19.0.dist-info/RECORD
