Metadata-Version: 2.4
Name: great-tables
Version: 0.19.0
Summary: Easily generate information-rich, publication-quality tables from Python.
Author-email: Richard Iannone <rich@posit.co>, Michael Chow <michael.chow@posit.co>
License: MIT License
Project-URL: homepage, https://github.com/posit-dev/great-tables
Project-URL: documentation, https://posit-dev.github.io/great-tables/
Keywords: tables
Classifier: Intended Audience :: End Users/Desktop
Classifier: Intended Audience :: Financial and Insurance Industry
Classifier: Intended Audience :: Science/Research
Classifier: Intended Audience :: Healthcare Industry
Classifier: Intended Audience :: Developers
Classifier: License :: OSI Approved :: MIT License
Classifier: Programming Language :: Python
Classifier: Programming Language :: Python :: 3.9
Classifier: Programming Language :: Python :: 3.10
Classifier: Programming Language :: Python :: 3.11
Classifier: Programming Language :: Python :: 3.12
Classifier: Programming Language :: Python :: 3.13
Classifier: Programming Language :: Python :: Implementation :: PyPy
Classifier: Topic :: Internet :: WWW/HTTP :: Dynamic Content
Classifier: Topic :: Software Development :: Libraries :: Python Modules
Classifier: Topic :: Text Processing :: Markup :: HTML
Classifier: Topic :: Scientific/Engineering :: Visualization
Requires-Python: >=3.9
License-File: LICENSE
Requires-Dist: commonmark>=0.9.1
Requires-Dist: faicons>=0.2.2
Requires-Dist: htmltools>=0.4.1
Requires-Dist: importlib-metadata
Requires-Dist: typing_extensions>=3.10.0.0
Requires-Dist: Babel>=2.13.1
Requires-Dist: importlib-resources
Provides-Extra: all
Requires-Dist: great_tables[extra]; extra == "all"
Requires-Dist: great_tables[dev]; extra == "all"
Provides-Extra: extra
Requires-Dist: css-inline>=0.14.1; extra == "extra"
Requires-Dist: selenium>=4.18.1; extra == "extra"
Requires-Dist: Pillow>=10.2.0; extra == "extra"
Provides-Extra: dev
Requires-Dist: great_tables[dev-no-pandas]; extra == "dev"
Requires-Dist: pandas; extra == "dev"
Requires-Dist: plotnine; extra == "dev"
Requires-Dist: numpy>=1.22.4; extra == "dev"
Provides-Extra: dev-no-pandas
Requires-Dist: ruff==0.8.0; extra == "dev-no-pandas"
Requires-Dist: jupyter; extra == "dev-no-pandas"
Requires-Dist: quartodoc>=0.11.0; python_version >= "3.9" and extra == "dev-no-pandas"
Requires-Dist: griffe==0.38.1; extra == "dev-no-pandas"
Requires-Dist: polars; extra == "dev-no-pandas"
Requires-Dist: pre-commit==2.15.0; extra == "dev-no-pandas"
Requires-Dist: pyarrow; extra == "dev-no-pandas"
Requires-Dist: pyright>=1.1.244; extra == "dev-no-pandas"
Requires-Dist: pytest>=3; extra == "dev-no-pandas"
Requires-Dist: pytest-cov; extra == "dev-no-pandas"
Requires-Dist: shiny; extra == "dev-no-pandas"
Requires-Dist: svg.py; extra == "dev-no-pandas"
Requires-Dist: syrupy; extra == "dev-no-pandas"
Dynamic: license-file
